pyulib/__init__.py
pyulib-0.1.2.dist-info/LICENSE
pyulib-0.1.2.dist-info/METADATA
pyulib-0.1.2.dist-info/WHEEL
pyulib-0.1.2.dist-info/top_level.txt
pyulib-0.1.2.dist-info/RECORD
