Metadata-Version: 2.1
Name: pyulib
Version: 0.1.2
Summary: python utility functions
Home-page: https://github.com/robert-lieck/pyulib
Author: Robert Lieck
Author-email: robert.lieck@durham.ac.uk
Classifier: Programming Language :: Python :: 3
Classifier: License :: OSI Approved :: GNU General Public License v3 (GPLv3)
Classifier: Operating System :: OS Independent
Requires-Python: >=3.6
License-File: LICENSE
